Metadata-Version: 1.1
Name: jrt-pypi
Version: 1.0.2
Summary: python lib
Home-page: https://github.com/HeavyCross/my_site
Author: runtao
Author-email: heavycross@163.com
License: MIT
Keywords: pypi
Platform: UNKNOWN
Classifier: Programming Language :: Python :: 2.7
